{
   "Alignment" : null,
   "Point" : null,
   "actors" : [
      {
         "Alignment" : [ 0, 0 ],
         "Alpha" : 1.0,
         "Angle" : 0.0,
         "Colour" : 4294967295,
         "Flip" : 0,
         "Position" : [ 0.0, -0.0 ],
         "Scale" : [ 1.0, 1.0 ],
         "Shown" : true,
         "sprite" : "bloonberry_00",
         "type" : 1,
         "uid" : 10
      },
      {
         "Alignment" : [ 0, 0 ],
         "Alpha" : 1.0,
         "Angle" : 0.0,
         "Colour" : 4294967295,
         "Flip" : 0,
         "Position" : [ 0.0, 0.0 ],
         "Scale" : [ 1.0, 1.0 ],
         "Shown" : false,
         "sprite" : "bloonberry_01",
         "type" : 1,
         "uid" : 1
      },
      {
         "Alignment" : [ 0, 0 ],
         "Alpha" : 1.0,
         "Angle" : 0.0,
         "Colour" : 4294967295,
         "Flip" : 0,
         "Position" : [ 0.0, 0.0 ],
         "Scale" : [ 1.0, 1.0 ],
         "Shown" : false,
         "sprite" : "bloonberry_02",
         "type" : 1,
         "uid" : 2
      },
      {
         "Alignment" : [ 0, 0 ],
         "Alpha" : 1.0,
         "Angle" : 0.0,
         "Colour" : 4294967295,
         "Flip" : 0,
         "Position" : [ 0.0, 1.0 ],
         "Scale" : [ 1.0, 1.0 ],
         "Shown" : false,
         "sprite" : "bloonberry_03",
         "type" : 1,
         "uid" : 3
      },
      {
         "Alignment" : [ 0, 0 ],
         "Alpha" : 1.0,
         "Angle" : 0.0,
         "Colour" : 4294967295,
         "Flip" : 0,
         "Position" : [ 0.0, 0.0 ],
         "Scale" : [ 1.0, 1.0 ],
         "Shown" : false,
         "sprite" : "bloonberry_04",
         "type" : 1,
         "uid" : 4
      },
      {
         "Alignment" : [ 0, 0 ],
         "Alpha" : 1.0,
         "Angle" : 0.0,
         "Colour" : 4294967295,
         "Flip" : 0,
         "Position" : [ 0.0, 0.0 ],
         "Scale" : [ 1.0, 1.0 ],
         "Shown" : false,
         "sprite" : "bloonberry_05",
         "type" : 1,
         "uid" : 5
      },
      {
         "Alignment" : [ 0, 0 ],
         "Alpha" : 1.0,
         "Angle" : 0.0,
         "Colour" : 4294967295,
         "Flip" : 0,
         "Position" : [ 0.0, 0.0 ],
         "Scale" : [ 1.0, 1.0 ],
         "Shown" : false,
         "sprite" : "bloonberry_06",
         "type" : 1,
         "uid" : 6
      },
      {
         "Alignment" : [ 0, 0 ],
         "Alpha" : 1.0,
         "Angle" : 0.0,
         "Colour" : 4294967295,
         "Flip" : 0,
         "Position" : [ 0.0, 0.0 ],
         "Scale" : [ 1.0, 1.0 ],
         "Shown" : false,
         "sprite" : "bloonberry_07",
         "type" : 1,
         "uid" : 7
      },
      {
         "Alignment" : [ 0, 0 ],
         "Alpha" : 1.0,
         "Angle" : 0.0,
         "Colour" : 4294967295,
         "Flip" : 0,
         "Position" : [ 0.0, 0.0 ],
         "Scale" : [ 1.0, 1.0 ],
         "Shown" : false,
         "sprite" : "bloonberry_08",
         "type" : 1,
         "uid" : 8
      },
      {
         "Alignment" : [ 0, 0 ],
         "Alpha" : 1.0,
         "Angle" : 0.0,
         "Colour" : 4294967295,
         "Flip" : 0,
         "Position" : [ 0.0, 0.0 ],
         "Scale" : [ 1.0, 1.0 ],
         "Shown" : false,
         "sprite" : "bloonberry_09",
         "type" : 1,
         "uid" : 9
      }
   ],
   "customvariables" : null,
   "events" : null,
   "labels" : null,
   "stageOptions" : {
      "SpriteInfo" : [
         {
            "SpriteInfo" : "bloonberry_00",
            "Texture" : "InGame"
         },
         {
            "SpriteInfo" : "bloonberry_01",
            "Texture" : "InGame"
         },
         {
            "SpriteInfo" : "bloonberry_02",
            "Texture" : "InGame"
         },
         {
            "SpriteInfo" : "bloonberry_03",
            "Texture" : "InGame"
         },
         {
            "SpriteInfo" : "bloonberry_04",
            "Texture" : "InGame"
         },
         {
            "SpriteInfo" : "bloonberry_05",
            "Texture" : "InGame"
         },
         {
            "SpriteInfo" : "bloonberry_06",
            "Texture" : "InGame"
         },
         {
            "SpriteInfo" : "bloonberry_07",
            "Texture" : "InGame"
         },
         {
            "SpriteInfo" : "bloonberry_08",
            "Texture" : "InGame"
         },
         {
            "SpriteInfo" : "bloonberry_09",
            "Texture" : "InGame"
         }
      ],
      "StageLength" : 20.0,
      "Version" : 1
   },
   "timelines" : [
      {
         "spriteuid" : 1,
         "stage" : [
            {
               "Alignment" : [ 0, 0 ],
               "Alpha" : 1.0,
               "Angle" : 0.0,
               "Colour" : 4294967295,
               "Flip" : 0,
               "Position" : [ 0.0, 0.0 ],
               "Scale" : [ 1.0, 1.0 ],
               "Shown" : false,
               "Time" : 0.0
            },
            {
               "Alignment" : [ 0, 0 ],
               "Alpha" : 1.0,
               "Angle" : 0.0,
               "Colour" : 4294967295,
               "Flip" : 0,
               "Position" : [ 0.0, 0.0 ],
               "Scale" : [ 1.0, 1.0 ],
               "Shown" : true,
               "Time" : 0.0
            },
            {
               "Alignment" : [ 0, 0 ],
               "Alpha" : 1.0,
               "Angle" : 0.0,
               "Colour" : 4294967295,
               "Flip" : 0,
               "Position" : [ 0.0, 0.0 ],
               "Scale" : [ 1.0, 1.0 ],
               "Shown" : false,
               "Time" : 0.05442176759243012
            },
            {
               "Alignment" : [ 0, 0 ],
               "Alpha" : 1.0,
               "Angle" : 0.0,
               "Colour" : 4294967295,
               "Flip" : 0,
               "Position" : [ 0.0, 0.0 ],
               "Scale" : [ 1.0, 1.0 ],
               "Shown" : true,
               "Time" : 0.02721088379621506
            }
         ]
      },
      {
         "spriteuid" : 2,
         "stage" : [
            {
               "Alignment" : [ 0, 0 ],
               "Alpha" : 1.0,
               "Angle" : 0.0,
               "Colour" : 4294967295,
               "Flip" : 0,
               "Position" : [ 0.0, 0.0 ],
               "Scale" : [ 1.0, 1.0 ],
               "Shown" : false,
               "Time" : 0.0
            },
            {
               "Alignment" : [ 0, 0 ],
               "Alpha" : 1.0,
               "Angle" : 0.0,
               "Colour" : 4294967295,
               "Flip" : 0,
               "Position" : [ 0.0, 0.0 ],
               "Scale" : [ 1.0, 1.0 ],
               "Shown" : true,
               "Time" : 0.05442176759243012
            },
            {
               "Alignment" : [ 0, 0 ],
               "Alpha" : 1.0,
               "Angle" : 0.0,
               "Colour" : 4294967295,
               "Flip" : 0,
               "Position" : [ 0.0, 0.0 ],
               "Scale" : [ 1.0, 1.0 ],
               "Shown" : false,
               "Time" : 0.0952380970120430
            }
         ]
      },
      {
         "spriteuid" : 3,
         "stage" : [
            {
               "Alignment" : [ 0, 0 ],
               "Alpha" : 1.0,
               "Angle" : 0.0,
               "Colour" : 4294967295,
               "Flip" : 0,
               "Position" : [ 0.0, 1.0 ],
               "Scale" : [ 1.0, 1.0 ],
               "Shown" : false,
               "Time" : 0.0
            },
            {
               "Alignment" : [ 0, 0 ],
               "Alpha" : 1.0,
               "Angle" : 0.0,
               "Colour" : 4294967295,
               "Flip" : 0,
               "Position" : [ 0.0, 1.0 ],
               "Scale" : [ 1.0, 1.0 ],
               "Shown" : true,
               "Time" : 0.0952380970120430
            },
            {
               "Alignment" : [ 0, 0 ],
               "Alpha" : 1.0,
               "Angle" : 0.0,
               "Colour" : 4294967295,
               "Flip" : 0,
               "Position" : [ 0.0, 1.0 ],
               "Scale" : [ 1.0, 1.0 ],
               "Shown" : false,
               "Time" : 0.1496598571538925
            }
         ]
      },
      {
         "spriteuid" : 4,
         "stage" : [
            {
               "Alignment" : [ 0, 0 ],
               "Alpha" : 1.0,
               "Angle" : 0.0,
               "Colour" : 4294967295,
               "Flip" : 0,
               "Position" : [ 0.0, 0.0 ],
               "Scale" : [ 1.0, 1.0 ],
               "Shown" : false,
               "Time" : 0.0
            },
            {
               "Alignment" : [ 0, 0 ],
               "Alpha" : 1.0,
               "Angle" : 0.0,
               "Colour" : 4294967295,
               "Flip" : 0,
               "Position" : [ 0.0, 0.0 ],
               "Scale" : [ 1.0, 1.0 ],
               "Shown" : true,
               "Time" : 0.1496598571538925
            },
            {
               "Alignment" : [ 0, 0 ],
               "Alpha" : 1.0,
               "Angle" : 0.0,
               "Colour" : 4294967295,
               "Flip" : 0,
               "Position" : [ 0.0, 0.0 ],
               "Scale" : [ 1.0, 1.0 ],
               "Shown" : false,
               "Time" : 0.2040816396474838
            }
         ]
      },
      {
         "spriteuid" : 5,
         "stage" : [
            {
               "Alignment" : [ 0, 0 ],
               "Alpha" : 1.0,
               "Angle" : 0.0,
               "Colour" : 4294967295,
               "Flip" : 0,
               "Position" : [ 0.0, 0.0 ],
               "Scale" : [ 1.0, 1.0 ],
               "Shown" : false,
               "Time" : 0.0
            },
            {
               "Alignment" : [ 0, 0 ],
               "Alpha" : 1.0,
               "Angle" : 0.0,
               "Colour" : 4294967295,
               "Flip" : 0,
               "Position" : [ 0.0, 0.0 ],
               "Scale" : [ 1.0, 1.0 ],
               "Shown" : true,
               "Time" : 0.2040816396474838
            },
            {
               "Alignment" : [ 0, 0 ],
               "Alpha" : 1.0,
               "Angle" : 0.0,
               "Colour" : 4294967295,
               "Flip" : 0,
               "Position" : [ 0.0, 0.0 ],
               "Scale" : [ 1.0, 1.0 ],
               "Shown" : false,
               "Time" : 0.2448979616165161
            }
         ]
      },
      {
         "spriteuid" : 6,
         "stage" : [
            {
               "Alignment" : [ 0, 0 ],
               "Alpha" : 1.0,
               "Angle" : 0.0,
               "Colour" : 4294967295,
               "Flip" : 0,
               "Position" : [ 0.0, 0.0 ],
               "Scale" : [ 1.0, 1.0 ],
               "Shown" : false,
               "Time" : 0.0
            },
            {
               "Alignment" : [ 0, 0 ],
               "Alpha" : 1.0,
               "Angle" : 0.0,
               "Colour" : 4294967295,
               "Flip" : 0,
               "Position" : [ 0.0, 2.0 ],
               "Scale" : [ 1.0, 1.0 ],
               "Shown" : true,
               "Time" : 0.2448979616165161
            },
            {
               "Alignment" : [ 0, 0 ],
               "Alpha" : 1.0,
               "Angle" : 0.0,
               "Colour" : 4294967295,
               "Flip" : 0,
               "Position" : [ 0.0, 2.0 ],
               "Scale" : [ 1.0, 1.0 ],
               "Shown" : false,
               "Time" : 0.2993197143077850
            }
         ]
      },
      {
         "spriteuid" : 7,
         "stage" : [
            {
               "Alignment" : [ 0, 0 ],
               "Alpha" : 1.0,
               "Angle" : 0.0,
               "Colour" : 4294967295,
               "Flip" : 0,
               "Position" : [ 0.0, 0.0 ],
               "Scale" : [ 1.0, 1.0 ],
               "Shown" : false,
               "Time" : 0.0
            },
            {
               "Alignment" : [ 0, 0 ],
               "Alpha" : 1.0,
               "Angle" : 0.0,
               "Colour" : 4294967295,
               "Flip" : 0,
               "Position" : [ 0.0, 0.0 ],
               "Scale" : [ 1.0, 1.0 ],
               "Shown" : true,
               "Time" : 0.2993197143077850
            },
            {
               "Alignment" : [ 0, 0 ],
               "Alpha" : 1.0,
               "Angle" : 0.0,
               "Colour" : 4294967295,
               "Flip" : 0,
               "Position" : [ 0.0, 0.0 ],
               "Scale" : [ 1.0, 1.0 ],
               "Shown" : false,
               "Time" : 0.3537414968013763
            }
         ]
      },
      {
         "spriteuid" : 8,
         "stage" : [
            {
               "Alignment" : [ 0, 0 ],
               "Alpha" : 1.0,
               "Angle" : 0.0,
               "Colour" : 4294967295,
               "Flip" : 0,
               "Position" : [ 0.0, 0.0 ],
               "Scale" : [ 1.0, 1.0 ],
               "Shown" : false,
               "Time" : 0.0
            },
            {
               "Alignment" : [ 0, 0 ],
               "Alpha" : 1.0,
               "Angle" : 0.0,
               "Colour" : 4294967295,
               "Flip" : 0,
               "Position" : [ 0.0, 0.0 ],
               "Scale" : [ 1.0, 1.0 ],
               "Shown" : true,
               "Time" : 0.3537414968013763
            },
            {
               "Alignment" : [ 0, 0 ],
               "Alpha" : 1.0,
               "Angle" : 0.0,
               "Colour" : 4294967295,
               "Flip" : 0,
               "Position" : [ 0.0, 0.0 ],
               "Scale" : [ 1.0, 1.0 ],
               "Shown" : false,
               "Time" : 0.4081632792949677
            }
         ]
      },
      {
         "spriteuid" : 9,
         "stage" : [
            {
               "Alignment" : [ 0, 0 ],
               "Alpha" : 1.0,
               "Angle" : 0.0,
               "Colour" : 4294967295,
               "Flip" : 0,
               "Position" : [ 0.0, 0.0 ],
               "Scale" : [ 1.0, 1.0 ],
               "Shown" : false,
               "Time" : 0.0
            },
            {
               "Alignment" : [ 0, 0 ],
               "Alpha" : 1.0,
               "Angle" : 0.0,
               "Colour" : 4294967295,
               "Flip" : 0,
               "Position" : [ 0.0, -2.0 ],
               "Scale" : [ 1.0, 1.0 ],
               "Shown" : true,
               "Time" : 0.4081632792949677
            }
         ]
      },
      {
         "spriteuid" : 10,
         "stage" : [
            {
               "Alignment" : [ 0, 0 ],
               "Alpha" : 1.0,
               "Angle" : 0.0,
               "Colour" : 4294967295,
               "Flip" : 0,
               "Position" : [ 0.0, -0.0 ],
               "Scale" : [ 1.0, 1.0 ],
               "Shown" : true,
               "Time" : 0.0
            },
            {
               "Alignment" : [ 0, 0 ],
               "Alpha" : 1.0,
               "Angle" : 0.0,
               "Colour" : 4294967295,
               "Flip" : 0,
               "Position" : [ 0.0, -0.0 ],
               "Scale" : [ 1.0, 1.0 ],
               "Shown" : false,
               "Time" : 0.02721088379621506
            }
         ]
      }
   ]
}
