{
    "Reflections": [
        "SpriteInfo.rxml"
    ],
    "Compiles": [
        {
            "SourceDir": "btdr_sprites",
            "Quality": "Ultra",
            "Results": [
                {
                    "Texture": "btdr_sprites.png",
                    "InfoXml": "btdr_sprites.xml"
                }
            ]
        },
        {
            "SourceDir": "btd6_sprites",
            "Quality": "Ultra",
            "Results": [
                {
                    "Texture": "btd6_sprites.png",
                    "InfoXml": "btd6_sprites.xml"
                }
            ]
        },
        {
            "SourceDir": "btdb_ported",
            "Quality": "High",
            "Results": [
                {
                    "Texture": "btdb_ported.png",
                    "InfoXml": "btdb_ported.xml"
                }
            ]
        }
    ]
}